asyncsshscript/__init__.py
asyncsshscript/host_session.py
asyncsshscript/script_type.py
asyncsshscript/version.py
asyncsshscript-0.1.0.dist-info/LICENSE
asyncsshscript-0.1.0.dist-info/METADATA
asyncsshscript-0.1.0.dist-info/WHEEL
asyncsshscript-0.1.0.dist-info/top_level.txt
asyncsshscript-0.1.0.dist-info/RECORD
