Metadata-Version: 2.1
Name: asyncsshscript
Version: 0.1.0
Summary: running remote commands or scripts with asyncssh
Home-page: https://github.com/NoevilMe/asyncsshscript
Author: NoevilMe
Author-email: surpass168@live.com
License: Eclipse Public License v2.0
Platform: Any
Classifier: Environment :: Console
Classifier: Intended Audience :: Developers
Classifier: License :: OSI Approved
Classifier: Operating System :: POSIX
Classifier: Programming Language :: Python :: 3.6
Classifier: Programming Language :: Python :: 3.7
Classifier: Programming Language :: Python :: 3.8
Classifier: Topic :: Internet
Classifier: Topic :: Security :: Cryptography
Classifier: Topic :: Software Development :: Libraries :: Python Modules
Classifier: Topic :: System :: Networking
Requires-Python: >= 3.6
Requires-Dist: asyncssh (>=2.2.0)
